klspy.cpython-311-darwin.so
klspy-2.0.3.dist-info/RECORD
klspy-2.0.3.dist-info/LICENSE
klspy-2.0.3.dist-info/WHEEL
klspy-2.0.3.dist-info/top_level.txt
klspy-2.0.3.dist-info/METADATA
