Metadata-Version: 2.1
Name: klspy
Version: 2.0.3
Summary: BLS signatures in c++ (python bindings)
Home-page: https://github.com/Chik-Network/kls-signatures
Author: Mariano Sorgente
Author-email: mariano@chiknetwork.com
Requires-Python: >=3.7
License-File: LICENSE
Requires-Dist: wheel
